gpas/__init__.py
gpas/cli.py
gpas/lib.py
gpas/misc.py
gpas/validation.py
gpas/data/__init__.py
gpas/data/countries/__init__.py
gpas/data/countries/countries_subdivisions.json
gpas/data/countries/generate_countries_subdivisions.py
gpas/data/refs/MN908947_no_polyA.fasta
gpas/data/refs/__init__.py
gpas_sc2-0.8.4.dist-info/LICENSE
gpas_sc2-0.8.4.dist-info/METADATA
gpas_sc2-0.8.4.dist-info/WHEEL
gpas_sc2-0.8.4.dist-info/entry_points.txt
gpas_sc2-0.8.4.dist-info/top_level.txt
gpas_sc2-0.8.4.dist-info/RECORD
