Metadata-Version: 2.1
Name: gpas-sc2
Version: 0.8.4
Summary: A command line client for the Global Pathogen Analysis Service
Home-page: https://github.com/GlobalPathogenAnalysisService/gpas-cli
Author: Bede Constantinides, Philip Fowler
Author-email: bedeabc@gmail.com
License: University of Oxford Academic License
Project-URL: Documentation, https://github.com/GlobalPathogenAnalysisService/gpas-cli
Project-URL: CI, https://github.com/GlobalPathogenAnalysisService/gpas-cli/actions
Project-URL: Source, https://github.com/GlobalPathogenAnalysisService/gpas-cli
Project-URL: Tracker, https://github.com/GlobalPathogenAnalysisService/gpas-cli/issues
Classifier: Environment :: Console
Classifier: Intended Audience :: Science/Research
Classifier: Natural Language :: English
Classifier: Operating System :: POSIX :: Linux
Classifier: Operating System :: MacOS :: MacOS X
Classifier: Programming Language :: Python :: 3.10
Requires-Python: >=3.10
License-File: LICENSE
Requires-Dist: httpx ==0.23.1
Requires-Dist: pandas ==1.5.2
Requires-Dist: pandera ==0.11.0
Requires-Dist: defopt ==6.4.0
Requires-Dist: tqdm ==4.64.1
Requires-Dist: tenacity ==8.1.0
